teamtrain_sdk/.DS_Store
teamtrain_sdk/bin/activate
teamtrain_sdk/bin/activate.csh
teamtrain_sdk/bin/activate.fish
teamtrain_sdk/bin/easy_install
teamtrain_sdk/bin/easy_install-3.7
teamtrain_sdk/bin/pip
teamtrain_sdk/bin/pip3
teamtrain_sdk/bin/pip3.7
teamtrain_sdk/bin/python
teamtrain_sdk/bin/python3
teamtrain_sdk/lib/python3.7/site-packages/easy_install.py
teamtrain_sdk/lib/python3.7/site-packages/pip/__init__.py
teamtrain_sdk/lib/python3.7/site-packages/pip/__main__.py
teamtrain_sdk/lib/python3.7/site-packages/pip/_internal/__init__.py
teamtrain_sdk/lib/python3.7/site-packages/pip/_internal/build_env.py
teamtrain_sdk/lib/python3.7/site-packages/pip/_internal/cache.py
teamtrain_sdk/lib/python3.7/site-packages/pip/_internal/cli/__init__.py
teamtrain_sdk/lib/python3.7/site-packages/pip/_internal/cli/autocompletion.py
teamtrain_sdk/lib/python3.7/site-packages/pip/_internal/cli/base_command.py
teamtrain_sdk/lib/python3.7/site-packages/pip/_internal/cli/cmdoptions.py
teamtrain_sdk/lib/python3.7/site-packages/pip/_internal/cli/main_parser.py
teamtrain_sdk/lib/python3.7/site-packages/pip/_internal/cli/parser.py
teamtrain_sdk/lib/python3.7/site-packages/pip/_internal/cli/status_codes.py
teamtrain_sdk/lib/python3.7/site-packages/pip/_internal/commands/__init__.py
teamtrain_sdk/lib/python3.7/site-packages/pip/_internal/commands/check.py
teamtrain_sdk/lib/python3.7/site-packages/pip/_internal/commands/completion.py
teamtrain_sdk/lib/python3.7/site-packages/pip/_internal/commands/configuration.py
teamtrain_sdk/lib/python3.7/site-packages/pip/_internal/commands/debug.py
teamtrain_sdk/lib/python3.7/site-packages/pip/_internal/commands/download.py
teamtrain_sdk/lib/python3.7/site-packages/pip/_internal/commands/freeze.py
teamtrain_sdk/lib/python3.7/site-packages/pip/_internal/commands/hash.py
teamtrain_sdk/lib/python3.7/site-packages/pip/_internal/commands/help.py
teamtrain_sdk/lib/python3.7/site-packages/pip/_internal/commands/install.py
teamtrain_sdk/lib/python3.7/site-packages/pip-19.2.3.dist-info/INSTALLER
teamtrain_sdk/lib/python3.7/site-packages/pip-19.2.3.dist-info/LICENSE.txt
teamtrain_sdk/lib/python3.7/site-packages/pip-19.2.3.dist-info/METADATA
teamtrain_sdk/lib/python3.7/site-packages/pip-19.2.3.dist-info/RECORD
teamtrain_sdk/lib/python3.7/site-packages/pip-19.2.3.dist-info/WHEEL
teamtrain_sdk/lib/python3.7/site-packages/pip-19.2.3.dist-info/entry_points.txt
teamtrain_sdk/lib/python3.7/site-packages/pip-19.2.3.dist-info/top_level.txt
teamtrain_sdk/lib/python3.7/site-packages/setuptools-41.2.0.dist-info/INSTALLER
teamtrain_sdk/lib/python3.7/site-packages/setuptools-41.2.0.dist-info/LICENSE
teamtrain_sdk/lib/python3.7/site-packages/setuptools-41.2.0.dist-info/METADATA
teamtrain_sdk/lib/python3.7/site-packages/setuptools-41.2.0.dist-info/RECORD
teamtrain_sdk/lib/python3.7/site-packages/setuptools-41.2.0.dist-info/WHEEL
teamtrain_sdk/lib/python3.7/site-packages/setuptools-41.2.0.dist-info/dependency_links.txt
teamtrain_sdk/lib/python3.7/site-packages/setuptools-41.2.0.dist-info/entry_points.txt
teamtrain_sdk/lib/python3.7/site-packages/setuptools-41.2.0.dist-info/top_level.txt
teamtrain_sdk/lib/python3.7/site-packages/setuptools-41.2.0.dist-info/zip-safe
teamtrain_sdk-0.1.6.dist-info/entry_points.txt
teamtrain_sdk-0.1.6.dist-info/WHEEL
teamtrain_sdk-0.1.6.dist-info/METADATA
teamtrain_sdk-0.1.6.dist-info/RECORD
