Metadata-Version: 2.1
Name: teamtrain-sdk
Version: 0.1.6
Summary: Python tools for interacting with the TeamTrain SDK
Author: Edd
Author-email: edward.abrahamsen-mills@safetyculture.io
Requires-Python: >=3.7,<4.0
Classifier: Programming Language :: Python :: 3
Classifier: Programming Language :: Python :: 3.7
Classifier: Programming Language :: Python :: 3.8
Requires-Dist: coloredlogs (>=14.0,<15.0)
Requires-Dist: pandas (>=1.0.3,<2.0.0)
Requires-Dist: requests (>=2.23.0,<3.0.0)
